{
  "color": {
    "base": {
      "huiRefNeutralVariantNeutralVariant12": { "value": "#1f1f27ff" },
      "huiRefNeutralVariantNeutralVariant40": { "value": "#5e5d67ff" },
      "huiRefPrimary25": { "value": "#201cb4ff" },
      "huiRefNeutralVariantNeutralVariant24": { "value": "#393841ff" },
      "huiRefNeutralNeutral25": { "value": "#3a3b3eff" },
      "huiSourceModesDarkScrim": { "value": "#000000ff" },
      "huiRefNeutralNeutral12": { "value": "#1e2023ff" },
      "huiRefErrorError17": { "value": "#5c0004ff" },
      "huiSourceModesDarkSurface": { "value": "#faf9fdff" },
      "huiRefNeutralVariantNeutralVariant35": { "value": "#52515bff" },
      "huiRefNeutralVariantNeutralVariant4": { "value": "#0d0e15ff" },
      "huiSourceModesDarkOnErrorContainer": { "value": "#410002ff" },
      "huiSourceModesDarkSurfaceTint": { "value": "#494bd6ff" },
      "huiRefErrorError70": { "value": "#ff897dff" },
      "huiRefErrorError60": { "value": "#ff5449ff" },
      "huiSourceModesDarkOnSurfaceVariant": { "value": "#46464fff" },
      "huiRefNeutralVariantNeutralVariant10": { "value": "#1b1b23ff" },
      "huiSourceModesDarkTertiaryFixed": { "value": "#6ffbbeff" },
      "huiSourceModesDarkErrorContainer": { "value": "#ffdad6ff" },
      "huiRefSecondarySecondary70": { "value": "#70aff7ff" },
      "huiSourceModesDarkInverseSurface": { "value": "#2f3033ff" },
      "huiRefErrorError96": { "value": "#fff0eeff" },
      "huiSourceModesDarkInverseOnSurface": { "value": "#f1f0f4ff" },
      "huiRefErrorError25": { "value": "#7e0007ff" },
      "huiRefTertiaryTertiary95": { "value": "#beffdbff" },
      "huiSourceModesDarkTertiaryFixedDim": { "value": "#4edea3ff" },
      "huiSourceModesDarkOnSecondaryContainer": { "value": "#001c37ff" },
      "huiRefTertiaryTertiary25": { "value": "#00452dff" },
      "huiSourceModesDarkOnSecondaryFixed": { "value": "#001c37ff" },
      "huiSourceModesDarkTertiary": { "value": "#006c49ff" },
      "huiRefSecondarySecondary96": { "value": "#eff4ffff" },
      "huiRefNeutralNeutral24": { "value": "#38393cff" },
      "huiSourceModesDarkSecondary": { "value": "#0961a4ff" },
      "huiRefSecondarySecondary92": { "value": "#dbe9ffff" },
      "huiRefPrimary92": { "value": "#e8e6ffff" },
      "huiSourceModesLightTertiaryFixedDim": { "value": "#4edea3ff" },
      "huiSourceModesLightOnErrorContainer": { "value": "#410002ff" },
      "huiRefNeutralVariantNeutralVariant25": { "value": "#3b3b43ff" },
      "huiRefNeutralNeutral35": { "value": "#515256ff" },
      "huiRefNeutralVariantNeutralVariant30": { "value": "#46464fff" },
      "huiRefErrorError87": { "value": "#ffcfc9ff" },
      "huiRefErrorError100": { "value": "#ffffffff" },
      "huiRefErrorError22": { "value": "#710005ff" },
      "huiRefTertiaryTertiary98": { "value": "#e8ffefff" },
      "huiRefTertiaryTertiary35": { "value": "#005f40ff" },
      "huiSourceModesDarkOnTertiaryFixedVariant": { "value": "#005236ff" },
      "huiRefTertiaryTertiary40": { "value": "#006c49ff" },
      "huiRefTertiaryTertiary12": { "value": "#002517ff" },
      "huiSourceModesDarkTertiaryContainer": { "value": "#6ffbbeff" },
      "huiRefSecondarySecondary100": { "value": "#ffffffff" },
      "huiRefSecondarySecondary17": { "value": "#002b4fff" },
      "huiRefPrimary96": { "value": "#f5f2ffff" },
      "huiRefNeutralNeutral87": { "value": "#dad9ddff" },
      "huiSourceModesLightTertiaryFixed": { "value": "#6ffbbeff" },
      "huiSourceModesLightOnSecondaryFixedVariant": { "value": "#00497eff" },
      "huiSourceModesLightPrimaryFixed": { "value": "#e1e0ffff" },
      "huiSourceModesDarkPrimaryContainer": { "value": "#e1e0ffff" },
      "huiRefNeutralVariantNeutralVariant87": { "value": "#dbd8e3ff" },
      "huiSourceModesDarkShadow": { "value": "#000000ff" },
      "huiRefNeutralNeutral92": { "value": "#e9e7ebff" },
      "huiRefErrorError35": { "value": "#a80710ff" },
      "huiRefNeutralVariantNeutralVariant50": { "value": "#777680ff" },
      "huiRefErrorError5": { "value": "#2d0001ff" },
      "huiSourceModesDarkOnSurface": { "value": "#1a1c1eff" },
      "huiSourceModesDarkOnError": { "value": "#ffffffff" },
      "huiRefTertiaryTertiary22": { "value": "#003d28ff" },
      "huiRefTertiaryTertiary0": { "value": "#000000ff" },
      "huiRefNeutralNeutral99": { "value": "#fdfbffff" },
      "huiSourceModesDarkOnPrimaryFixed": { "value": "#07006cff" },
      "huiRefSecondarySecondary25": { "value": "#003d6bff" },
      "huiSourceModesDarkSecondaryContainer": { "value": "#d2e4ffff" },
      "huiRefPrimary94": { "value": "#eeecffff" },
      "huiRefNeutralNeutral20": { "value": "#2f3033ff" },
      "huiSourceModesLightOnTertiaryFixed": { "value": "#002113ff" },
      "huiSourceModesLightOnSecondary": { "value": "#ffffffff" },
      "huiBlack": { "value": "#000000ff" },
      "huiRefPrimary99": { "value": "#fffbffff" },
      "huiSourceModesDarkOnPrimary": { "value": "#ffffffff" },
      "huiRefErrorError40": { "value": "#ba1a1aff" },
      "huiRefErrorError0": { "value": "#000000ff" },
      "huiRefErrorError10": { "value": "#410002ff" },
      "huiRefTertiaryTertiary6": { "value": "#00180dff" },
      "huiRefSecondarySecondary98": { "value": "#f8f9ffff" },
      "huiRefTertiaryTertiary10": { "value": "#002113ff" },
      "huiRefSecondarySecondary50": { "value": "#357abfff" },
      "huiRefSecondarySecondary80": { "value": "#a0caffff" },
      "huiRefPrimary87": { "value": "#d7d6ffff" },
      "huiRefNeutralNeutral70": { "value": "#ababaeff" },
      "huiSourceModesLightSecondaryFixedDim": { "value": "#a0caffff" },
      "huiSourceModesLightSecondaryFixed": { "value": "#d2e4ffff" },
      "huiSourceModesLightSecondaryContainer": { "value": "#d2e4ffff" },
      "huiRefPrimary24": { "value": "#1d17b2ff" },
      "huiSourceModesDarkPrimary": { "value": "#494bd6ff" },
      "huiSourceModesLightOnBackground": { "value": "#1a1c1eff" },
      "huiRefSecondarySecondary10": { "value": "#001c37ff" },
      "huiSourceModesLightBackground": { "value": "#fdfbffff" },
      "huiRefNeutralVariantNeutralVariant100": { "value": "#ffffffff" },
      "huiSourceModesLightOnSurface": { "value": "#1a1c1eff" },
      "huiRefNeutralVariantNeutralVariant92": { "value": "#eae7f2ff" },
      "huiRefNeutralVariantNeutralVariant94": { "value": "#efecf7ff" },
      "huiRefNeutralNeutral98": { "value": "#faf9fdff" },
      "huiRefNeutralVariantNeutralVariant22": { "value": "#34343cff" },
      "huiRefNeutralNeutral0": { "value": "#000000ff" },
      "huiRefNeutralNeutral17": { "value": "#292a2dff" },
      "huiRefNeutralVariantNeutralVariant96": { "value": "#f5f2fdff" },
      "huiRefNeutralVariantNeutralVariant17": { "value": "#292931ff" },
      "huiRefNeutralNeutral6": { "value": "#121316ff" },
      "huiSourceModesDarkOutlineVariant": { "value": "#c8c5d0ff" },
      "huiRefNeutralNeutral4": { "value": "#0d0e11ff" },
      "huiRefNeutralNeutral5": { "value": "#101114ff" },
      "huiSourceModesDarkOutline": { "value": "#777680ff" },
      "huiRefNeutralNeutral10": { "value": "#1a1c1eff" },
      "huiRefErrorError99": { "value": "#fffbffff" },
      "huiSourceModesDarkBackground": { "value": "#fdfbffff" },
      "huiSourceModesDarkSurfaceVariant": { "value": "#e4e1ecff" },
      "huiSourceModesDarkOnTertiaryFixed": { "value": "#002113ff" },
      "huiRefTertiaryTertiary20": { "value": "#003824ff" },
      "huiRefTertiaryTertiary24": { "value": "#00422bff" },
      "huiRefNeutralNeutral80": { "value": "#c7c6caff" },
      "huiRefNeutralVariantNeutralVariant6": { "value": "#13131aff" },
      "huiRefNeutralNeutral90": { "value": "#e3e2e6ff" },
      "huiRefErrorError98": { "value": "#fff8f7ff" },
      "huiRefNeutralVariantNeutralVariant20": { "value": "#303038ff" },
      "huiRefErrorError80": { "value": "#ffb4abff" },
      "huiRefErrorError90": { "value": "#ffdad6ff" },
      "huiRefErrorError20": { "value": "#690005ff" },
      "huiRefTertiaryTertiary94": { "value": "#aeffd5ff" },
      "huiRefTertiaryTertiary90": { "value": "#6ffbbeff" },
      "huiRefTertiaryTertiary4": { "value": "#001209ff" },
      "huiSourceModesDarkOnSecondaryFixedVariant": { "value": "#00497eff" },
      "huiSourceModesDarkOnBackground": { "value": "#1a1c1eff" },
      "huiRefErrorError95": { "value": "#ffedeaff" },
      "huiRefErrorError4": { "value": "#280001ff" },
      "huiRefErrorError24": { "value": "#790006ff" },
      "huiRefTertiaryTertiary92": { "value": "#86ffc6ff" },
      "huiSourceModesDarkError": { "value": "#ba1a1aff" },
      "huiRefTertiaryTertiary87": { "value": "#65f3b6ff" },
      "huiSourceModesDarkOnPrimaryContainer": { "value": "#07006cff" },
      "huiSourceModesDarkSecondaryFixed": { "value": "#d2e4ffff" },
      "huiSourceModesDarkPrimaryFixedDim": { "value": "#c0c1ffff" },
      "huiRefTertiaryTertiary70": { "value": "#26c289ff" },
      "huiRefNeutralNeutral100": { "value": "#ffffffff" },
      "huiRefSecondarySecondary94": { "value": "#e5eeffff" },
      "huiRefPrimary100": { "value": "#ffffffff" },
      "huiRefErrorError50": { "value": "#de3730ff" },
      "huiRefNeutralVariantNeutralVariant5": { "value": "#101018ff" },
      "huiRefErrorError92": { "value": "#ffe2deff" },
      "huiRefErrorError94": { "value": "#ffe9e6ff" },
      "huiSourceModesDarkOnTertiaryContainer": { "value": "#002113ff" },
      "huiRefErrorError30": { "value": "#93000aff" },
      "huiRefTertiaryTertiary100": { "value": "#ffffffff" },
      "huiRefTertiaryTertiary99": { "value": "#f4fff6ff" },
      "huiRefTertiaryTertiary96": { "value": "#cdffe2ff" },
      "huiRefNeutralNeutral95": { "value": "#f1f0f4ff" },
      "huiRefTertiaryTertiary60": { "value": "#00a572ff" },
      "huiRefSecondarySecondary24": { "value": "#003b68ff" },
      "huiRefErrorError12": { "value": "#490002ff" },
      "huiRefErrorError6": { "value": "#310001ff" },
      "huiRefTertiaryTertiary80": { "value": "#4edea3ff" },
      "huiSourceModesDarkSecondaryFixedDim": { "value": "#a0caffff" },
      "huiSourceModesDarkOnTertiary": { "value": "#ffffffff" },
      "huiRefNeutralNeutral94": { "value": "#eeedf1ff" },
      "huiRefTertiaryTertiary17": { "value": "#00311fff" },
      "huiRefSecondarySecondary95": { "value": "#eaf1ffff" },
      "huiRefSecondarySecondary22": { "value": "#003660ff" },
      "huiRefSecondarySecondary60": { "value": "#5394daff" },
      "huiKeyColorsSecondary": { "value": "#64748aff" },
      "huiRefSecondarySecondary12": { "value": "#00213dff" },
      "huiRefSecondarySecondary6": { "value": "#001429ff" },
      "huiRefNeutralNeutral40": { "value": "#5e5e62ff" },
      "huiSourceModesLightOnTertiary": { "value": "#ffffffff" },
      "huiWhite": { "value": "#ffffffff" },
      "huiSourceModesLightSurfaceDim": { "value": "#dad9ddff" },
      "huiSourceModesLightErrorContainer": { "value": "#ffdad6ff" },
      "huiSourceModesLightOnSecondaryFixed": { "value": "#001c37ff" },
      "huiSourceModesLightOnPrimary": { "value": "#ffffffff" },
      "huiSourceModesLightOnPrimaryFixedVariant": { "value": "#2f2ebeff" },
      "huiSourceModesLightSurfaceContainerLow": { "value": "#f4f3f7ff" },
      "huiRefSecondarySecondary30": { "value": "#00497eff" },
      "huiRefSecondarySecondary90": { "value": "#d2e4ffff" },
      "huiSourceModesDarkOnSecondary": { "value": "#ffffffff" },
      "huiSourceModesDarkOnPrimaryFixedVariant": { "value": "#2f2ebeff" },
      "huiRefPrimary98": { "value": "#fcf8ffff" },
      "huiRefNeutralNeutral96": { "value": "#f4f3f7ff" },
      "huiRefNeutralNeutral60": { "value": "#909094ff" },
      "huiSourceModesLightOnTertiaryContainer": { "value": "#002113ff" },
      "huiSourceModesLightOnPrimaryFixed": { "value": "#07006cff" },
      "huiRefSecondarySecondary0": { "value": "#000000ff" },
      "huiRefPrimary50": { "value": "#6366f1ff" },
      "huiSourceModesLightSurfaceContainerHighest": { "value": "#e3e2e6ff" },
      "huiRefTertiaryTertiary50": { "value": "#00885dff" },
      "huiRefTertiaryTertiary30": { "value": "#005236ff" },
      "huiRefTertiaryTertiary5": { "value": "#00150bff" },
      "huiRefSecondarySecondary35": { "value": "#005592ff" },
      "huiRefSecondarySecondary87": { "value": "#c3dcffff" },
      "huiSourceModesLightSurfaceContainerLowest": { "value": "#ffffffff" },
      "huiRefNeutralVariantNeutralVariant98": { "value": "#fcf8ffff" },
      "huiRefNeutralNeutral50": { "value": "#76777aff" },
      "huiSourceModesLightOnError": { "value": "#ffffffff" },
      "huiSourceModesLightTertiaryContainer": { "value": "#6ffbbeff" },
      "huiSourceModesLightOnPrimaryContainer": { "value": "#07006cff" },
      "huiRefNeutralVariantNeutralVariant0": { "value": "#000000ff" },
      "huiSourceModesLightSurfaceBright": { "value": "#faf9fdff" },
      "huiRefPrimary20": { "value": "#1000a9ff" },
      "huiSourceModesDarkSurfaceContainer": { "value": "#eeedf1ff" },
      "huiSourceModesDarkPrimaryFixed": { "value": "#e1e0ffff" },
      "huiRefSecondarySecondary5": { "value": "#001225ff" },
      "huiKeyColorsNeutral": { "value": "#6b7280ff" },
      "huiRefNeutralNeutral22": { "value": "#343538ff" },
      "huiSourceModesLightOnTertiaryFixedVariant": { "value": "#005236ff" },
      "huiSourceModesLightSecondary": { "value": "#0961a4ff" },
      "huiSourceModesLightPrimaryContainer": { "value": "#e1e0ffff" },
      "huiSourceModesLightShadow": { "value": "#000000ff" },
      "huiSourceModesLightSurfaceContainerHigh": { "value": "#e9e7ebff" },
      "huiRefSecondarySecondary20": { "value": "#003259ff" },
      "huiRefPrimary90": { "value": "#e1e0ffff" },
      "huiRefPrimary0": { "value": "#000000ff" },
      "huiRefNeutralVariantNeutralVariant70": { "value": "#acaab4ff" },
      "huiSourceModesLightSurfaceContainer": { "value": "#eeedf1ff" },
      "huiSourceModesLightScrim": { "value": "#000000ff" },
      "huiSourceModesLightSurfaceVariant": { "value": "#e4e1ecff" },
      "huiSourceModesDarkSurfaceContainerHighest": { "value": "#e3e2e6ff" },
      "huiSourceModesDarkInversePrimary": { "value": "#c0c1ffff" },
      "huiSourceModesLightOnSurfaceVariant": { "value": "#46464fff" },
      "huiSourceSeed": { "value": "#6366f1ff" },
      "huiRefNeutralVariantNeutralVariant95": { "value": "#f2effaff" },
      "huiSourceModesLightOutline": { "value": "#777680ff" },
      "huiSourceModesDarkSurfaceDim": { "value": "#dad9ddff" },
      "huiRefNeutralVariantNeutralVariant80": { "value": "#c8c5d0ff" },
      "huiRefPrimary17": { "value": "#0d0096ff" },
      "huiRefPrimary80": { "value": "#c0c1ffff" },
      "huiRefPrimary10": { "value": "#07006cff" },
      "huiRefNeutralVariantNeutralVariant90": { "value": "#e4e1ecff" },
      "huiRefNeutralVariantNeutralVariant60": { "value": "#918f9aff" },
      "huiKeyColorsTertiary": { "value": "#10b981ff" },
      "huiRefNeutralNeutral30": { "value": "#46474aff" },
      "huiSourceModesLightTertiary": { "value": "#006c49ff" },
      "huiSourceModesLightOnSecondaryContainer": { "value": "#001c37ff" },
      "huiRefPrimary22": { "value": "#170daeff" },
      "huiRefPrimary95": { "value": "#f2efffff" },
      "huiRefPrimary30": { "value": "#2f2ebeff" },
      "huiSourceModesLightInverseSurface": { "value": "#2f3033ff" },
      "huiRefPrimary60": { "value": "#8083ffff" },
      "huiRefPrimary12": { "value": "#080078ff" },
      "huiKeyColorsPrimary": { "value": "#6366f1ff" },
      "huiSourceModesLightOutlineVariant": { "value": "#c8c5d0ff" },
      "huiSourceModesLightInverseOnSurface": { "value": "#f1f0f4ff" },
      "huiSourceModesLightSurface": { "value": "#faf9fdff" },
      "huiRefPrimary6": { "value": "#040054ff" },
      "huiSourceModesLightInversePrimary": { "value": "#c0c1ffff" },
      "huiRefSecondarySecondary99": { "value": "#fdfcffff" },
      "huiRefSecondarySecondary4": { "value": "#000f21ff" },
      "huiRefPrimary4": { "value": "#030045ff" },
      "huiSourceModesLightError": { "value": "#ba1a1aff" },
      "huiSourceModesLightPrimaryFixedDim": { "value": "#c0c1ffff" },
      "huiSourceModesLightPrimary": { "value": "#494bd6ff" },
      "huiRefNeutralVariantNeutralVariant99": { "value": "#fffbffff" },
      "huiRefPrimary40": { "value": "#494bd6ff" },
      "huiSourceModesLightSurfaceTint": { "value": "#494bd6ff" },
      "huiRefPrimary70": { "value": "#a0a3ffff" },
      "huiRefPrimary5": { "value": "#03004dff" },
      "huiSourceModesDarkSurfaceContainerLowest": { "value": "#ffffffff" },
      "huiRefSecondarySecondary40": { "value": "#0961a4ff" },
      "huiSourceModesDarkSurfaceContainerHigh": { "value": "#e9e7ebff" },
      "huiSourceModesDarkSurfaceBright": { "value": "#faf9fdff" },
      "huiRefPrimary35": { "value": "#3c3dcaff" },
      "huiSourceModesDarkSurfaceContainerLow": { "value": "#f4f3f7ff" }
    }
  }
}
